LICENSE
iter_collect/__init__.py
iter_collect/py.typed
iter_collect-0.0.5.1.dist-info/LICENSE
iter_collect-0.0.5.1.dist-info/METADATA
iter_collect-0.0.5.1.dist-info/WHEEL
iter_collect-0.0.5.1.dist-info/RECORD
